{
    "kids": [],
    "uid": "1399",
    "parent": "",
    "text": "【详情通报！#北京一新增输入病例曾在小区居家停留#】4月5日下午，第72场北京市新型冠状病毒肺炎疫情防控工作新闻发布会召开。北京市疾控中心副主任庞星火通报了昨日境外输入确诊病例情况。庞星火表示，4月4日，本市新增报告境外输入新冠肺炎病例1例。某女，无业。2019年9月前往英国伦敦探亲。2020年3月19日，与丈夫乘坐国航CA938航班从英国伦敦出发，20日到达北京首都机场。抵京后，夫妻经海关检疫，申报健康无异常，遂至集中医学观察点进行隔离观察。25日，隔离点动员隔离观察人员进行新冠病毒核酸检测，夫妻均未参加。30日晚，该女士出现咳嗽、咳痰、恶心、精神不振等症状，自行服药，在工作人员询问其健康状况时未报告。4月3日，夫妻解除隔离，由集中隔离点车辆转运至市内集散点，后由家人驾车接回小区，在小区保安处出示隔离证明、进行登记、测体温后回家。3日晚患者出现高热，达39℃，4日上午由家人驾车送至北京朝阳医院就诊，采集患者标本进行新型冠状病毒核酸检测，结果呈阳性，即由120救护车送至定点医院治疗。结合患者境外旅居史、肺部影像、血液检查等诊断依据，4日诊断为确诊病例，临床分型为重型病症。已对密切接触者采取相应管理措施。庞星火表示，患者在隔离观察期间出现症状，在工作人员询问时未报告，导致延误治疗，就诊时已发展为重型，进入重症监护室治疗。庞星火提示大家，在医学观察期间出现任何身体异常，均要及时如实报告健康状况，否则可能延误治疗时机，甚至增加传染他人的风险。（北京青年报）",
    "mid": "1399",
    "date": "2020/4/5 16:34"
}