{
    "kids": [],
    "uid": "2151",
    "parent": "",
    "text": "【#美国新冠肺炎超369万例#，#美国至少39州实施不同形式的口罩令#】美国约翰斯·霍普金斯大学数据显示，截至美东时间18日下午6时36分，美国已有新冠病毒感染病例3697554例，其中包括死亡病例139948例。与该系统7月17日下午5时38分的数据相比，美国新增感染病例70497例，新增死亡病例960例。美国总统特朗普在接受福克斯新闻采访时表示，他不会发布要求美国人佩戴口罩以减缓新冠病毒传播的命令。“我希望人们享有一定的自由”， 特朗普称，“我不赞成如果所有人都戴上口罩，一切疫情就会消失的说法”。在采访中，媒体提到了美国疾控中心主任雷德菲尔德的话，即如果每个人都戴口罩，美国可以在4到6周内控制病毒传播。对此说法，特朗普表示他并不认同。他还说，公共卫生官员最初曾说人们无需戴口罩。不过，随后特朗普又说，“他相信口罩，口罩是好的”。目前，美国至少有39个州以及首都华盛顿哥伦比亚特区都已经实施了不同形式的口罩令。（人民日报记者 郑琪）",
    "mid": "2151",
    "date": "2020/7/19 7:02"
}