{
    "kids": [],
    "uid": "278",
    "parent": "",
    "text": "中铁十九局意大利建方舱医院招工简章 招聘工种： 钩机司机、铲车司机、压路机司机、平地机司机、翻斗车司机、厨师、修理工、小工。 合同期限：1月 招聘要求： 1.无犯罪记录 2.身体健康，无先天性心脏病、传染病、高血压等。 工资待遇： 1. 压路机司机、翻斗车司机：300000元/月； 2. 平地机司机、钩机司机：250000元/月； 3. 铲车司机：230000元/月； 4. 厨师：170000元/月； 5. 修理工：220000元/月； 6. 小工：160000元/月； 7. 电焊工：150000元/月； 8. 推土机：230000元/月； 9. 瓦工：350000元/月； 10.吊车：250000元/月 工作时间：早7:30-12:00，下午1:00-5:30. 其他待遇： 1. 合同期内由雇主负责办理重大意外保险、健康保险等各类保险； 2. 往返路费雇主承担； 3. 合同期内由雇主免费提供食宿； 4. 工资月结，统一工商银行打卡发薪； 5. 办理周期：于2020年4月28日离境。电话13554128586",
    "mid": "278",
    "date": "2020/3/24"
}